fastanime/__init__.py
fastanime/__main__.py
fastanime/fastanime.py
fastanime/assets/normalizer.json
fastanime/assets/defaults/ascii-art
fastanime/assets/defaults/fastanime-worker.template.service
fastanime/assets/defaults/fzf-opts
fastanime/assets/defaults/rofi-themes/confirm.rasi
fastanime/assets/defaults/rofi-themes/input.rasi
fastanime/assets/defaults/rofi-themes/main.rasi
fastanime/assets/defaults/rofi-themes/preview.rasi
fastanime/assets/graphql/allanime/queries/anime.gql
fastanime/assets/graphql/allanime/queries/episodes.gql
fastanime/assets/graphql/allanime/queries/search.gql
fastanime/assets/graphql/anilist/mutations/delete-list-entry.gql
fastanime/assets/graphql/anilist/mutations/mark-read.gql
fastanime/assets/graphql/anilist/mutations/media-list.gql
fastanime/assets/graphql/anilist/queries/logged-in-user.gql
fastanime/assets/graphql/anilist/queries/media-airing-schedule.gql
fastanime/assets/graphql/anilist/queries/media-characters.gql
fastanime/assets/graphql/anilist/queries/media-list-item.gql
fastanime/assets/graphql/anilist/queries/media-list.gql
fastanime/assets/graphql/anilist/queries/media-recommendations.gql
fastanime/assets/graphql/anilist/queries/media-relations.gql
fastanime/assets/graphql/anilist/queries/notifications.gql
fastanime/assets/graphql/anilist/queries/reviews.gql
fastanime/assets/graphql/anilist/queries/search.gql
fastanime/assets/graphql/anilist/queries/user-info.gql
fastanime/assets/icons/logo.ico
fastanime/assets/icons/logo.png
fastanime/assets/scripts/fzf/airing-schedule-info.template.sh
fastanime/assets/scripts/fzf/airing-schedule-preview.template.sh
fastanime/assets/scripts/fzf/character-info.template.sh
fastanime/assets/scripts/fzf/character-preview.template.sh
fastanime/assets/scripts/fzf/dynamic-preview.template.sh
fastanime/assets/scripts/fzf/episode-info.template.sh
fastanime/assets/scripts/fzf/info.template.sh
fastanime/assets/scripts/fzf/preview.template.sh
fastanime/assets/scripts/fzf/review-info.template.sh
fastanime-3.1.0.dist-info/METADATA
fastanime-3.1.0.dist-info/WHEEL
fastanime-3.1.0.dist-info/entry_points.txt
fastanime-3.1.0.dist-info/licenses/LICENSE
fastanime-3.1.0.dist-info/RECORD
