Metadata-Version: 2.4
Name: fastanime
Version: 3.1.0
Summary: A browser anime site experience from the terminal
License-Expression: Unlicense
License-File: LICENSE
Requires-Python: >=3.10
Requires-Dist: click>=8.1.7
Requires-Dist: httpx>=0.28.1
Requires-Dist: inquirerpy>=0.3.4
Requires-Dist: pydantic>=2.11.7
Requires-Dist: rich>=13.9.2
Provides-Extra: discord
Requires-Dist: pypresence>=4.3.0; extra == 'discord'
Provides-Extra: download
Requires-Dist: pycryptodomex>=3.23.0; extra == 'download'
Requires-Dist: yt-dlp>=2025.7.21; extra == 'download'
Provides-Extra: lxml
Requires-Dist: lxml>=6.0.0; extra == 'lxml'
Provides-Extra: mpv
Requires-Dist: mpv>=1.0.7; extra == 'mpv'
Provides-Extra: notifications
Requires-Dist: dbus-python>=1.4.0; extra == 'notifications'
Requires-Dist: plyer>=2.1.0; extra == 'notifications'
Provides-Extra: standard
Requires-Dist: dbus-python>=1.4.0; extra == 'standard'
Requires-Dist: lxml>=6.0.0; extra == 'standard'
Requires-Dist: plyer>=2.1.0; extra == 'standard'
Requires-Dist: pycryptodomex>=3.23.0; extra == 'standard'
Requires-Dist: thefuzz>=0.22.1; extra == 'standard'
Requires-Dist: yt-dlp>=2025.7.21; extra == 'standard'
Provides-Extra: torrent
Requires-Dist: libtorrent>=2.0.11; extra == 'torrent'
Provides-Extra: torrents
Requires-Dist: libtorrent>=2.0.11; extra == 'torrents'
